nr_vocabularies_model_builder/__init__.py
nr_vocabularies_model_builder/ui_components_specs.py
nr_vocabularies_model_builder/version.py
nr_vocabularies_model_builder/models/__init__.py
nr_vocabularies_model_builder/models/model.json
nr_vocabularies_model_builder-1.0.2.dist-info/METADATA
nr_vocabularies_model_builder-1.0.2.dist-info/WHEEL
nr_vocabularies_model_builder-1.0.2.dist-info/entry_points.txt
nr_vocabularies_model_builder-1.0.2.dist-info/top_level.txt
nr_vocabularies_model_builder-1.0.2.dist-info/RECORD
